pretzelai_server/__init__.py
pretzelai_server/_version.py
pretzelai_server/handlers.py
pretzelai_server-0.1.3.data/data/etc/jupyter/jupyter_server_config.d/pretzelai_server.json
pretzelai_server-0.1.3.data/data/share/jupyter/labextensions/pretzelai-server/package.json
pretzelai_server-0.1.3.data/data/share/jupyter/labextensions/pretzelai-server/static/509.63efa2fe78520ad42c8c.js
pretzelai_server-0.1.3.data/data/share/jupyter/labextensions/pretzelai-server/static/728.50094926dd5fc865aa17.js
pretzelai_server-0.1.3.data/data/share/jupyter/labextensions/pretzelai-server/static/remoteEntry.e68fb5e6c0437b7c14c5.js
pretzelai_server-0.1.3.data/data/share/jupyter/labextensions/pretzelai-server/static/style.js
pretzelai_server-0.1.3.data/data/share/jupyter/labextensions/pretzelai-server/static/third-party-licenses.json
pretzelai_server-0.1.3.data/data/share/jupyter/labextensions/pretzelai-server/install.json
pretzelai_server-0.1.3.dist-info/METADATA
pretzelai_server-0.1.3.dist-info/WHEEL
pretzelai_server-0.1.3.dist-info/licenses/LICENSE
pretzelai_server-0.1.3.dist-info/RECORD
