Metadata-Version: 2.3
Name: pretzelai_server
Version: 0.1.3
Dynamic: Keywords
Summary: Pretzel's Server Extension
Project-URL: Homepage, https://github.com/pretzelai/pretzelai-server-ext
Project-URL: Bug Tracker, https://github.com/pretzelai/pretzelai-server-ext/issues
Project-URL: Repository, https://github.com/pretzelai/pretzelai-server-ext.git
Author-email: Pretzel AI GmbH <founders@withpretzel.com>
License:                     GNU AFFERO GENERAL PUBLIC LICENSE
License-File: LICENSE
Classifier: Framework :: Jupyter
Classifier: Framework :: Jupyter :: JupyterLab
Classifier: Framework :: Jupyter :: JupyterLab :: 4
Classifier: Framework :: Jupyter :: JupyterLab :: Extensions
Classifier: Framework :: Jupyter :: JupyterLab :: Extensions :: Prebuilt
Classifier: License :: OSI Approved :: BSD License
Classifier: Programming Language :: Python
Classifier: Programming Language :: Python :: 3
Classifier: Programming Language :: Python :: 3.8
Classifier: Programming Language :: Python :: 3.9
Classifier: Programming Language :: Python :: 3.10
Classifier: Programming Language :: Python :: 3.11
Classifier: Programming Language :: Python :: 3.12
Requires-Python: >=3.8
Requires-Dist: anthropic==0.31.0
Requires-Dist: fastembed<1,>=0.3.3
Requires-Dist: jupyter-server<3,>=2.0.1
